verifyannotations/__init__.py
verifyannotations/verifyannotations.py
verifyannotations/verifypascalvoc_annotations.py
verifyannotations-1.0.dist-info/LICENSE.txt
verifyannotations-1.0.dist-info/METADATA
verifyannotations-1.0.dist-info/WHEEL
verifyannotations-1.0.dist-info/top_level.txt
verifyannotations-1.0.dist-info/RECORD
