Metadata-Version: 2.1
Name: verifyannotations
Version: 1.0
Summary: verify YOLO data annotations
Home-page: https://github.com/george-mountain/verifyannotations
Download-URL: https://github.com/george-mountain/verifyannotations/archive/refs/tags/1.0.tar.gz
Author: George Mountain
Author-email: engrmountain@gmail.com
License: MIT
Project-URL: Bug Tracker, https://github.com/george-mountain/verifyannotations/issues
Keywords: pypi,computer vision,machine learning,data annotations,deep learning,verifyannotations,verify data annotations,plot yolo bounding boxes
Classifier: Development Status :: 3 - Alpha
Classifier: Intended Audience :: Developers
Classifier: License :: OSI Approved :: MIT License
Classifier: Programming Language :: Python :: 3
Classifier: Programming Language :: Python :: 3.8
Classifier: Programming Language :: Python :: 3.9
Classifier: Programming Language :: Python :: 3.10
Classifier: Programming Language :: Python :: 3.11
License-File: LICENSE.txt
Requires-Dist: opencv-python
Requires-Dist: colorama
Requires-Dist: tqdm
